pyems/__init__.py
pyems/boundary.py
pyems/calc.py
pyems/coordinate.py
pyems/feed.py
pyems/field_dump.py
pyems/kicad.py
pyems/material.py
pyems/mesh.py
pyems/nf2ff.py
pyems/pcb.py
pyems/physical_constant.py
pyems/port.py
pyems/priority.py
pyems/probe.py
pyems/simulation.py
pyems/structure.py
pyems/utilities.py
py_ems-0.1.0.dist-info/WHEEL
py_ems-0.1.0.dist-info/METADATA
py_ems-0.1.0.dist-info/RECORD
